python_weixin-0.3.4.dist-info/METADATA
python_weixin-0.3.4.dist-info/RECORD
python_weixin-0.3.4.dist-info/WHEEL
python_weixin-0.3.4.dist-info/pbr.json
python_weixin-0.3.4.dist-info/top_level.txt
python_weixin-0.3.4.dist-info/zip-safe
weixin/__init__.py
weixin/bind.py
weixin/client.py
weixin/config.py
weixin/helper.py
weixin/json_import.py
weixin/msg_template.py
weixin/oauth2.py
weixin/pay.py
weixin/reply.py
weixin/response.py
weixin/lib/Sample.py
weixin/lib/WXBizMsgCrypt.py
weixin/lib/__init__.py
weixin/lib/ierror.py
weixin/lib/wxcrypt.py
