Metadata-Version: 2.1
Name: python-weixin
Version: 0.3.4
Summary: Python Weixin API client support wechat-app
Home-page: https://github.com/gusibi/python-weixin
Author: gusibi
Author-email: cacique1103@gmail.com
License: BSD
Download-URL: https://github.com/gusibi/python-weixin/archive/master.zip
Keywords: python-weixin,weixin,wechat,sdk,weapp,wxapp
Platform: UNKNOWN
Requires-Dist: simplejson
Requires-Dist: requests
Requires-Dist: chardet
Requires-Dist: six
Requires-Dist: lxml
Requires-Dist: xmltodict
Requires-Dist: pycrypto
